[{"model": "users.user", "pk": 1, "fields": {"password": "1001", "last_login": null, "is_superuser": false, "first_name": "", "last_name": "", "is_staff": false, "is_active": true, "date_joined": "2024-09-17T00:51:07.676Z", "email": "1@mail.ru", "avatar": "", "phone": null, "city": null, "groups": [], "user_permissions": []}}, {"model": "users.user", "pk": 2, "fields": {"password": "1001", "last_login": null, "is_superuser": false, "first_name": "", "last_name": "", "is_staff": false, "is_active": true, "date_joined": "2024-09-17T10:00:50.077Z", "email": "2@mail.ru", "avatar": "", "phone": null, "city": null, "groups": [], "user_permissions": []}}, {"model": "users.payments", "pk": 1, "fields": {"user": 1, "date_pay": "2024-09-17", "course": 3, "lesson": null, "amount": 100000, "way": "1"}}, {"model": "users.payments", "pk": 2, "fields": {"user": 1, "date_pay": "2024-09-17", "course": 2, "lesson": null, "amount": 120000, "way": "0"}}, {"model": "users.payments", "pk": 3, "fields": {"user": 2, "date_pay": "2024-09-17", "course": null, "lesson": 3, "amount": 12000, "way": "0"}}, {"model": "users.payments", "pk": 4, "fields": {"user": 2, "date_pay": "2024-09-17", "course": null, "lesson": 4, "amount": 11000, "way": "0"}}]